corpus_pax/__init__.py
corpus_pax/__main__.py
corpus_pax/articles.py
corpus_pax/entities.py
corpus_pax/github.py
corpus_pax/resources.py
corpus_pax/templates/update_member_id_on_insert_email.sql
corpus_pax/utils.py
corpus_pax-0.1.27.dist-info/LICENSE
corpus_pax-0.1.27.dist-info/METADATA
corpus_pax-0.1.27.dist-info/WHEEL
corpus_pax-0.1.27.dist-info/RECORD
